LICENSE
README.md
setup.py
exception_decouple/__init__.py
exception_decouple/decorator.py
exception_decouple.egg-info/PKG-INFO
exception_decouple.egg-info/SOURCES.txt
exception_decouple.egg-info/dependency_links.txt
exception_decouple.egg-info/top_level.txt